{
  "cig": "631936267D",
  "strutturaProponente": {
    "codiceFiscaleProp": "80088230018",
    "denominazione": "Universit\u00c3\u00a0 degli Studi di Torino"
  },
  "oggetto": "Fornitura e posa arredi per la sede di Via S. Ottavio,54.\nCUP: D11E14000390005 - CIG: 631936267D\nRDO Mepa nr. 885890",
  "sceltaContraente": "04-PROCEDURA NEGOZIATA SENZA PREVIA PUBBLICAZIONE DEL BANDO",
  "partecipanti": {
    "partecipante": [
      {
        "codiceFiscale": "11143440011",
        "ragioneSociale": "011CONTRACT SRL"
      },
      {
        "codiceFiscale": "00570170035",
        "ragioneSociale": "ALFA S.A.S. DI CISLAGHI MAURIZIA & C."
      },
      {
        "codiceFiscale": "00887180248",
        "ragioneSociale": "ARES LINE spa"
      },
      {
        "codiceFiscale": "10352570013",
        "ragioneSociale": "BC SPAZI S.r.l."
      },
      {
        "codiceFiscale": "02132510039",
        "ragioneSociale": "GT TOMASINI SAS"
      },
      {
        "codiceFiscale": "02655090344",
        "ragioneSociale": "LAMM"
      },
      {
        "codiceFiscale": "00962130290",
        "ragioneSociale": "MECO"
      },
      {
        "codiceFiscale": "02098740026",
        "ragioneSociale": "MOSCA UFFICIO STILE"
      }
    ]
  },
  "aggiudicatari": {
    "aggiudicatario": {
      "codiceFiscale": "11143440011",
      "ragioneSociale": "011CONTRACT SRL"
    }
  },
  "importoAggiudicazione": "63606.38",
  "tempiCompletamento": null,
  "importoSommeLiquidate": "63606.38"
}