{
  "cig": "7231004D42",
  "strutturaProponente": {
    "codiceFiscaleProp": "00518460019",
    "denominazione": "Politecnico di Torino"
  },
  "oggetto": "Procedura negoziata sotto soglia comunitaria, ai sensi dell\u00e2\u0080\u0099art. 36, comma 2, lett. B del D. Lgs. 50/2016, per l\u00e2\u0080\u0099affidamento del servizio di autotrasporto passeggeri su strada effettuato con autobus",
  "sceltaContraente": "08-AFFIDAMENTO IN ECONOMIA - COTTIMO FIDUCIARIO",
  "partecipanti": {
    "partecipante": [
      {
        "codiceFiscale": "00173940065",
        "ragioneSociale": "CANIGGIABUS SRL"
      },
      {
        "codiceFiscale": "00280830043",
        "ragioneSociale": "SAV AUTOLINEE S.R.L."
      },
      {
        "codiceFiscale": "00060360054",
        "ragioneSociale": "AUTOLINEE GIACHINO"
      },
      {
        "codiceFiscale": "02867770048",
        "ragioneSociale": "GARELLIVIAGGI DI GARELLI GIANFRANCO"
      },
      {
        "codiceFiscale": "04446480016",
        "ragioneSociale": "COSTA ANTONINO"
      },
      {
        "codiceFiscale": "02096960030",
        "ragioneSociale": "EASYWAY S.A.S. DI LORIS LEONE E C."
      },
      {
        "codiceFiscale": "01271060020",
        "ragioneSociale": "ANDREOLI TIZIANO"
      },
      {
        "codiceFiscale": "00519860019",
        "ragioneSociale": "CAVOURESE S.P.A."
      },
      {
        "codiceFiscale": "00893890012",
        "ragioneSociale": "BUS COMPANY SRL"
      },
      {
        "codiceFiscale": "08716150019",
        "ragioneSociale": "D.E.S."
      },
      {
        "codiceFiscale": "08153920015",
        "ragioneSociale": "LE RADICI E LE ALI"
      },
      {
        "codiceFiscale": "00475230017",
        "ragioneSociale": "VIAGGI FURNO SRL"
      },
      {
        "codiceFiscale": "01357740057",
        "ragioneSociale": "BERARDI BUS DI BERARDI DANILO"
      },
      {
        "codiceFiscale": "03454120043",
        "ragioneSociale": "GALLO GIANNI"
      },
      {
        "codiceFiscale": "01432870069",
        "ragioneSociale": "AUTONOLEGGI MORTARA"
      },
      {
        "codiceFiscale": "00973350069",
        "ragioneSociale": "C.I.T. CONSORZIO INTERCOMUNALE TRASPORTI S.P.A."
      },
      {
        "codiceFiscale": "09689090018",
        "ragioneSociale": "RASTEL BOGIN SNC DI RASTEL BOGIN GIOVANNI & C."
      },
      {
        "codiceFiscale": "03240360044",
        "ragioneSociale": "GIORDANINO SAMUELE"
      },
      {
        "codiceFiscale": "04922550019",
        "ragioneSociale": "BOUCHARD ENZO & C. SNC"
      },
      {
        "codiceFiscale": "02797390040",
        "ragioneSociale": "GUIDO BUS SNC DI MURIALDO GUIDO ANDREA & C."
      },
      {
        "codiceFiscale": "09501980016",
        "ragioneSociale": "LINEA AZZURRA SRL"
      },
      {
        "codiceFiscale": "03021360049",
        "ragioneSociale": "PAOLO GREGORIO AUTONOLEGGIO"
      },
      {
        "codiceFiscale": "00974680050",
        "ragioneSociale": "HOLLIBUS AUTOSERVIZI DI OLLINO SERGIO, LUCA E CHRISTIAN SNC"
      },
      {
        "codiceFiscale": "01894660016",
        "ragioneSociale": "MARIETTA ALDO"
      },
      {
        "codiceFiscale": "03665110049",
        "ragioneSociale": "CONSORZIO DGR BUS"
      },
      {
        "codiceFiscale": "03563000045",
        "ragioneSociale": "DOGLIANI SNC DI ROVERE ROBERTO E C."
      },
      {
        "codiceFiscale": "02368060048",
        "ragioneSociale": "SASSO & ROATTINO SNC DI SASSO MADDALENA & C"
      },
      {
        "codiceFiscale": "00113970032",
        "ragioneSociale": "S.A.F. SOCIET\u00c3\u0080 AUTOSERVIZI FONTANETO S.R.L."
      },
      {
        "codiceFiscale": "03089970010",
        "ragioneSociale": "GHI.ME SRL"
      },
      {
        "codiceFiscale": "03291130049",
        "ragioneSociale": "M.R. TRASPORTI SAS"
      },
      {
        "codiceFiscale": "02852990049",
        "ragioneSociale": "EUROBUS CUNEO SRL"
      },
      {
        "codiceFiscale": "02350560047",
        "ragioneSociale": "AUTO MATTIAUDA SRL"
      },
      {
        "codiceFiscale": "03376700047",
        "ragioneSociale": "PANGEA VIAGGI DI BAUSANO SIMONETTA E MANDRILE ELENA S.N.C."
      },
      {
        "codiceFiscale": "02821920044",
        "ragioneSociale": "OFFICINA GHIGLIA DI GHIGLIA ALBINO & C. S.N.C."
      },
      {
        "codiceFiscale": "01700280025",
        "ragioneSociale": "B.MOTORS DI BOTTA LUIGI"
      },
      {
        "codiceFiscale": "02831800046",
        "ragioneSociale": "SOCIETA' COOPERATIVA ARMONIA WORK S.C.S.A.R.L."
      },
      {
        "codiceFiscale": "01861030045",
        "ragioneSociale": "AUTOLINEE VALLE PESIO S.R.L."
      },
      {
        "codiceFiscale": "04206210017",
        "ragioneSociale": "AUTONOLEGGI SAVINO SRL"
      },
      {
        "codiceFiscale": "00125480038",
        "ragioneSociale": "AUTOSERVIZI COMAZZI S.R.L."
      },
      {
        "codiceFiscale": "01025640051",
        "ragioneSociale": "GELOSOBUS S.R.L."
      },
      {
        "codiceFiscale": "02126170030",
        "ragioneSociale": "ECO.DEMA DI DE MARCO PIETRO"
      }
    ]
  },
  "aggiudicatari": {
    "aggiudicatario": {
      "codiceFiscale": "00519860019",
      "ragioneSociale": "CAVOURESE S.P.A."
    }
  },
  "importoAggiudicazione": "120000.00",
  "tempiCompletamento": null,
  "importoSommeLiquidate": "00.00"
}