{
  "cig": "745733752B",
  "strutturaProponente": {
    "codiceFiscaleProp": "00518460019",
    "denominazione": "Politecnico di Torino"
  },
  "oggetto": "Macchina di prova uniassiale/torsionale - LOTTO 2",
  "sceltaContraente": "08-AFFIDAMENTO IN ECONOMIA - COTTIMO FIDUCIARIO",
  "partecipanti": {
    "partecipante": {
      "codiceFiscale": "00468990015",
      "ragioneSociale": "ITW Test and Measurement Italia Srl"
    }
  },
  "aggiudicatari": {
    "aggiudicatario": {
      "codiceFiscale": "00468990015",
      "ragioneSociale": "ITW Test and Measurement Italia Srl"
    }
  },
  "importoAggiudicazione": "121000.00",
  "tempiCompletamento": {
    "dataInizio": "2018-06-26",
    "dataUltimazione": "2018-06-26"
  },
  "importoSommeLiquidate": "00.00"
}