{
  "cig": "75755662D4",
  "strutturaProponente": {
    "codiceFiscaleProp": "00518460019",
    "denominazione": "Politecnico di Torino"
  },
  "oggetto": "CIG: 75755662D4 - CUP: E12F17001220006 - n. 2 server bi-processore x86-64 1U 1536 GB ram e n. 2 server bi-processore x86-64 1U con 768 Gb ram",
  "sceltaContraente": "08-AFFIDAMENTO IN ECONOMIA - COTTIMO FIDUCIARIO",
  "partecipanti": {
    "partecipante": {
      "codiceFiscale": "01226710331",
      "ragioneSociale": "EMILIA INFORMATICA S.R.L."
    }
  },
  "aggiudicatari": {
    "aggiudicatario": {
      "codiceFiscale": "01226710331",
      "ragioneSociale": "EMILIA INFORMATICA S.R.L."
    }
  },
  "importoAggiudicazione": "79024.00",
  "tempiCompletamento": {
    "dataInizio": "2018-11-13",
    "dataUltimazione": "2018-11-13"
  },
  "importoSommeLiquidate": "00.00"
}