{
  "cig": "Z041B0ABA7",
  "strutturaProponente": {
    "codiceFiscaleProp": "80088230018",
    "denominazione": "Universita' degli Studi di Torino - STUDI UMANISTICI"
  },
  "oggetto": "PRENOTAZ. BIGLIETT. FERROVIARIA DOCENTE GAIA COTTINO_CONVEGNO PROFF. BONIFAZIO-FARGIONE",
  "sceltaContraente": "23-AFFIDAMENTO IN ECONOMIA - AFFIDAMENTO DIRETTO",
  "partecipanti": {
    "partecipante": {
      "codiceFiscale": "00465850014",
      "ragioneSociale": "EDENTOURS S.N.C."
    }
  },
  "aggiudicatari": {
    "aggiudicatario": {
      "codiceFiscale": "00465850014",
      "ragioneSociale": "EDENTOURS S.N.C."
    }
  },
  "importoAggiudicazione": "119.80",
  "tempiCompletamento": {
    "dataInizio": "2016-11-10",
    "dataUltimazione": "2016-11-13"
  },
  "importoSommeLiquidate": "119.80"
}