{
  "cig": "Z0720A95F2",
  "strutturaProponente": {
    "codiceFiscaleProp": "00518460019",
    "denominazione": "Politecnico di Torino"
  },
  "oggetto": "Ultrabook  e materiale accessorio.",
  "sceltaContraente": "23-AFFIDAMENTO IN ECONOMIA - AFFIDAMENTO DIRETTO",
  "partecipanti": {
    "partecipante": [
      {
        "codiceFiscale": "02778750246",
        "ragioneSociale": "SOLUZIONE UFFICIO S.R.L."
      },
      {
        "codiceFiscale": "NSTLSN74M26F158R",
        "ragioneSociale": "ANASTASI ALESSANDRO ANASTASI ALESSANDRO"
      }
    ]
  },
  "aggiudicatari": {
    "aggiudicatario": {
      "codiceFiscale": "02778750246",
      "ragioneSociale": "SOLUZIONE UFFICIO S.R.L."
    }
  },
  "importoAggiudicazione": "1491.00",
  "tempiCompletamento": {
    "dataInizio": "2017-12-18",
    "dataUltimazione": "2017-12-18"
  },
  "importoSommeLiquidate": "00.00"
}