{
  "cig": "Z082697859",
  "strutturaProponente": {
    "codiceFiscaleProp": "80088230018",
    "denominazione": "Universita' degli Studi di Torino - Biblioteca Federata di Medicina \"Ferdinando Rossi\""
  },
  "oggetto": "Rinnovo banca dati Cinahl complete",
  "sceltaContraente": "26-AFFIDAMENTO DIRETTO IN ADESIONE AD ACCORDO QUADRO/CONVENZIONE",
  "partecipanti": {
    "partecipante": {
      "codiceFiscale": "11164410018",
      "ragioneSociale": "EBSCO Information Services SrL"
    }
  },
  "aggiudicatari": {
    "aggiudicatario": {
      "codiceFiscale": "11164410018",
      "ragioneSociale": "EBSCO Information Services SrL"
    }
  },
  "importoAggiudicazione": "22482.00",
  "tempiCompletamento": {
    "dataInizio": "2019-01-01",
    "dataUltimazione": "2019-01-31"
  },
  "importoSommeLiquidate": "0.00"
}