{
  "cig": "Z091455662",
  "strutturaProponente": {
    "codiceFiscaleProp": "80088230018",
    "denominazione": "Universit\u00c3\u00a0 degli Studi di Torino"
  },
  "oggetto": "BO 519/15 MATERIALE LABORATORIO",
  "sceltaContraente": "23-AFFIDAMENTO IN ECONOMIA - AFFIDAMENTO DIRETTO",
  "partecipanti": {
    "partecipante": {
      "codiceFiscale": "08355250013",
      "ragioneSociale": "APPEN-LAB SRL"
    }
  },
  "aggiudicatari": {
    "aggiudicatario": {
      "codiceFiscale": "08355250013",
      "ragioneSociale": "APPEN-LAB SRL"
    }
  },
  "importoAggiudicazione": "648.55",
  "tempiCompletamento": null,
  "importoSommeLiquidate": "648.55"
}