{
  "cig": "Z0F1821C1E",
  "strutturaProponente": {
    "codiceFiscaleProp": "80088230018",
    "denominazione": "Universita' degli Studi di Torino - CHIMICA"
  },
  "oggetto": "SOGGIORNI  SAKHNO + IVANCHENKO - MARTRA",
  "sceltaContraente": "23-AFFIDAMENTO IN ECONOMIA - AFFIDAMENTO DIRETTO",
  "partecipanti": {
    "partecipante": {
      "codiceFiscale": "06440290010",
      "ragioneSociale": "E.D.I.S.U. Ente Regionale per il Diritto allo Studio Universitario del Piemonte"
    }
  },
  "aggiudicatari": {
    "aggiudicatario": {
      "codiceFiscale": "06440290010",
      "ragioneSociale": "E.D.I.S.U. Ente Regionale per il Diritto allo Studio Universitario del Piemonte"
    }
  },
  "importoAggiudicazione": "204.54",
  "tempiCompletamento": {
    "dataInizio": "2016-09-01",
    "dataUltimazione": "2016-09-12"
  },
  "importoSommeLiquidate": "204.54"
}