{
  "cig": "Z1B167D956",
  "strutturaProponente": {
    "codiceFiscaleProp": "80088230018",
    "denominazione": "Universit\u00c3\u00a0 degli Studi di Torino"
  },
  "oggetto": "TAXI PER PROF. PECCATI IL 12/10/15 TRATTA CLE/TORINO PORTA NUOVA -CONV.\"DIRITTO E MATEMATICA \" PROF.SA SCOMPARIN 12/10/15",
  "sceltaContraente": "23-AFFIDAMENTO IN ECONOMIA - AFFIDAMENTO DIRETTO",
  "partecipanti": {
    "partecipante": {
      "identificativoFiscaleEstero": "01563740016",
      "ragioneSociale": "SOC.COOPER. PRONTO TAXI TORINESE 5737 SOC. COOP. A R L ."
    }
  },
  "aggiudicatari": {
    "aggiudicatario": {
      "identificativoFiscaleEstero": "01563740016",
      "ragioneSociale": "SOC.COOPER. PRONTO TAXI TORINESE 5737 SOC. COOP. A R L ."
    }
  },
  "importoAggiudicazione": "12.00",
  "tempiCompletamento": null,
  "importoSommeLiquidate": "12.00"
}