{
  "cig": "Z1C21A9138",
  "strutturaProponente": {
    "codiceFiscaleProp": "00518460019",
    "denominazione": "Politecnico di Torino"
  },
  "oggetto": "Dispositivo palmare",
  "sceltaContraente": "23-AFFIDAMENTO IN ECONOMIA - AFFIDAMENTO DIRETTO",
  "partecipanti": {
    "partecipante": [
      {
        "codiceFiscale": "NSTLSN74M26F158R",
        "ragioneSociale": "ANASTASI ALESSANDRO ANASTASI ALESSANDRO"
      },
      {
        "codiceFiscale": "02509001208",
        "ragioneSociale": "MA.PO.  S.R.L.  UNIPERSONALE"
      },
      {
        "codiceFiscale": "04102680826",
        "ragioneSociale": "L.B. CLIMA DI LO PORTO FRANCESCO & C. SNC"
      },
      {
        "codiceFiscale": "05475890876",
        "ragioneSociale": "I-DEAL S.R.L."
      },
      {
        "codiceFiscale": "03359340837",
        "ragioneSociale": "ALCANTARA S.R.L."
      },
      {
        "codiceFiscale": "02191040647",
        "ragioneSociale": "NET.COM SRL"
      },
      {
        "codiceFiscale": "02778750246",
        "ragioneSociale": "SOLUZIONE UFFICIO S.R.L."
      },
      {
        "codiceFiscale": "01696300837",
        "ragioneSociale": "ELAR DIVISION SICILIA SRL"
      }
    ]
  },
  "aggiudicatari": {
    "aggiudicatario": {
      "codiceFiscale": "NSTLSN74M26F158R",
      "ragioneSociale": "ANASTASI ALESSANDRO ANASTASI ALESSANDRO"
    }
  },
  "importoAggiudicazione": "778.00",
  "tempiCompletamento": {
    "dataInizio": "2018-01-30",
    "dataUltimazione": "2018-01-30"
  },
  "importoSommeLiquidate": "778.00"
}