{
  "cig": "Z222237390",
  "strutturaProponente": {
    "codiceFiscaleProp": "00518460019",
    "denominazione": "Politecnico di Torino"
  },
  "oggetto": "CIG: Z222237390 - n. 3 servizi di coffee break dolce e salato per 10 persone  in data 21/02/2018 e 22/02/2018",
  "sceltaContraente": "23-AFFIDAMENTO IN ECONOMIA - AFFIDAMENTO DIRETTO",
  "partecipanti": {
    "partecipante": [
      {
        "codiceFiscale": "00311310379",
        "ragioneSociale": "CAMST SOC. COOP A.R.L."
      },
      {
        "codiceFiscale": "09965670012",
        "ragioneSociale": "CORNER S.R.L."
      }
    ]
  },
  "aggiudicatari": {
    "aggiudicatario": {
      "codiceFiscale": "00311310379",
      "ragioneSociale": "CAMST SOC. COOP A.R.L."
    }
  },
  "importoAggiudicazione": "200.00",
  "tempiCompletamento": {
    "dataInizio": "2018-02-16",
    "dataUltimazione": "2018-02-20"
  },
  "importoSommeLiquidate": "170.00"
}