{
  "cig": "Z2520E5320",
  "strutturaProponente": {
    "codiceFiscaleProp": "00518460019",
    "denominazione": "Politecnico di Torino"
  },
  "oggetto": "20171121 Cena Seminario Prof. Weisbrod - Ristorante La Badessa",
  "sceltaContraente": "23-AFFIDAMENTO IN ECONOMIA - AFFIDAMENTO DIRETTO",
  "partecipanti": {
    "partecipante": {
      "codiceFiscale": "07250050015",
      "ragioneSociale": "LA BADESSA S.A.S. DI RATCLIF R. & C."
    }
  },
  "aggiudicatari": {
    "aggiudicatario": {
      "codiceFiscale": "07250050015",
      "ragioneSociale": "LA BADESSA S.A.S. DI RATCLIF R. & C."
    }
  },
  "importoAggiudicazione": "483.70",
  "tempiCompletamento": {
    "dataInizio": "2017-11-21",
    "dataUltimazione": "2017-12-31"
  },
  "importoSommeLiquidate": "449.15"
}