{
  "cig": "Z2D1658333",
  "strutturaProponente": {
    "codiceFiscaleProp": "80088230018",
    "denominazione": "Universit\u00c3\u00a0 degli Studi di Torino"
  },
  "oggetto": "mat. lab. estero",
  "sceltaContraente": "23-AFFIDAMENTO IN ECONOMIA - AFFIDAMENTO DIRETTO",
  "partecipanti": {
    "partecipante": {
      "identificativoFiscaleEstero": "842179912",
      "ragioneSociale": "Jackson ImmunoResearch Europe Ltd"
    }
  },
  "aggiudicatari": {
    "aggiudicatario": {
      "identificativoFiscaleEstero": "842179912",
      "ragioneSociale": "Jackson ImmunoResearch Europe Ltd"
    }
  },
  "importoAggiudicazione": "0.00",
  "tempiCompletamento": null,
  "importoSommeLiquidate": "365.00"
}