{
  "cig": "Z33209680E",
  "strutturaProponente": {
    "codiceFiscaleProp": "00518460019",
    "denominazione": "Politecnico di Torino"
  },
  "oggetto": "Pubblicazione su quotidiani degli estratti dei bandi di gara",
  "sceltaContraente": "23-AFFIDAMENTO IN ECONOMIA - AFFIDAMENTO DIRETTO",
  "partecipanti": {
    "partecipante": {
      "codiceFiscale": "04656100726",
      "ragioneSociale": "INFO S.R.L."
    }
  },
  "aggiudicatari": {
    "aggiudicatario": {
      "codiceFiscale": "04656100726",
      "ragioneSociale": "INFO S.R.L."
    }
  },
  "importoAggiudicazione": "1100.00",
  "tempiCompletamento": {
    "dataInizio": "2017-10-25",
    "dataUltimazione": "2017-10-25"
  },
  "importoSommeLiquidate": "1100.00"
}