{
  "cig": "Z351BD82A5",
  "strutturaProponente": {
    "codiceFiscaleProp": "80088230018",
    "denominazione": "Universit\u00c3\u00a0 degli Studi di Torino"
  },
  "oggetto": "Man ord imp. elettrici e speciali. Esecuzione di interventi manutentivi con sostituzione di componenti ai fini del mantenimento efficienza/efficacia dell'impianto elettrico, anche a seguito ricezione di help desk, da realizzarsi presso sedi Unito.",
  "sceltaContraente": "26-AFFIDAMENTO DIRETTO IN ADESIONE AD ACCORDO QUADRO/CONVENZIONE",
  "partecipanti": {
    "partecipante": {
      "codiceFiscale": "05651220013",
      "ragioneSociale": "CHIAVAZZA srl"
    }
  },
  "aggiudicatari": {
    "aggiudicatario": {
      "codiceFiscale": "05651220013",
      "ragioneSociale": "CHIAVAZZA srl"
    }
  },
  "importoAggiudicazione": "9996.00",
  "tempiCompletamento": null,
  "importoSommeLiquidate": "9994.90"
}