{
  "cig": "Z351EF8B7D",
  "strutturaProponente": {
    "codiceFiscaleProp": "00518460019",
    "denominazione": "Politecnico di Torino"
  },
  "oggetto": "CIG: Z351EF8B7D - Upgrade Std software Mathematica da v2.x \u00e2\u0080\u0093 v11.0 EDU per la licenza L4740-0584",
  "sceltaContraente": "23-AFFIDAMENTO IN ECONOMIA - AFFIDAMENTO DIRETTO",
  "partecipanti": {
    "partecipante": {
      "codiceFiscale": "01408650511",
      "ragioneSociale": "ADALTA SNC"
    }
  },
  "aggiudicatari": {
    "aggiudicatario": {
      "codiceFiscale": "01408650511",
      "ragioneSociale": "ADALTA SNC"
    }
  },
  "importoAggiudicazione": "362.50",
  "tempiCompletamento": {
    "dataInizio": "2017-06-13",
    "dataUltimazione": "2017-06-13"
  },
  "importoSommeLiquidate": "362.50"
}