{
  "cig": "Z3F257DC45",
  "strutturaProponente": {
    "codiceFiscaleProp": "00518460019",
    "denominazione": "Politecnico di Torino"
  },
  "oggetto": "CIG Z3F257DC4 - Apple MacBook Pro 15\" + accessori + estensione garanzia",
  "sceltaContraente": "23-AFFIDAMENTO IN ECONOMIA - AFFIDAMENTO DIRETTO",
  "partecipanti": {
    "partecipante": [
      {
        "codiceFiscale": "08687680960",
        "ragioneSociale": "SOLPA srl"
      },
      {
        "codiceFiscale": "NSTLSN74M26F158R",
        "ragioneSociale": "ANASTASI ALESSANDRO ANASTASI ALESSANDRO"
      },
      {
        "codiceFiscale": "05984211218",
        "ragioneSociale": "R-STORE spa"
      },
      {
        "codiceFiscale": "05685740721",
        "ragioneSociale": "C&C  CONSULTING  S.R.L."
      }
    ]
  },
  "aggiudicatari": {
    "aggiudicatario": {
      "codiceFiscale": "05685740721",
      "ragioneSociale": "C&C  CONSULTING  S.R.L."
    }
  },
  "importoAggiudicazione": "4267.00",
  "tempiCompletamento": {
    "dataInizio": "2018-11-08",
    "dataUltimazione": "2018-11-08"
  },
  "importoSommeLiquidate": "4267.00"
}