{
  "cig": "Z3F25244C9",
  "strutturaProponente": {
    "codiceFiscaleProp": "00518460019",
    "denominazione": "Politecnico di Torino"
  },
  "oggetto": "CIG Z3F25244C9 - MATERIALE CONSUMO INFORMATICO",
  "sceltaContraente": "23-AFFIDAMENTO IN ECONOMIA - AFFIDAMENTO DIRETTO",
  "partecipanti": {
    "partecipante": [
      {
        "codiceFiscale": "NSTLSN74M26F158R",
        "ragioneSociale": "ANASTASI ALESSANDRO ANASTASI ALESSANDRO"
      },
      {
        "codiceFiscale": "07575360016",
        "ragioneSociale": "EPICI S.R.L."
      },
      {
        "codiceFiscale": "10578740150",
        "ragioneSociale": "RS COMPONENTS S.R.L."
      },
      {
        "codiceFiscale": "04864781002",
        "ragioneSociale": "CARTO COPY SERVICE S.R.L."
      },
      {
        "codiceFiscale": "04160880243",
        "ragioneSociale": "STEMA SRL"
      },
      {
        "codiceFiscale": "12968611009",
        "ragioneSociale": "OFFICINEAPOGEO SRLS"
      }
    ]
  },
  "aggiudicatari": {
    "aggiudicatario": {
      "codiceFiscale": "10578740150",
      "ragioneSociale": "RS COMPONENTS S.R.L."
    }
  },
  "importoAggiudicazione": "240.00",
  "tempiCompletamento": {
    "dataInizio": "2018-10-23",
    "dataUltimazione": "2018-10-23"
  },
  "importoSommeLiquidate": "240.00"
}