{
  "cig": "Z441D4D3DC",
  "strutturaProponente": {
    "codiceFiscaleProp": "00518460019",
    "denominazione": "Politecnico di Torino"
  },
  "oggetto": "CIG  Z441D4D3DC - scheda acquisizione dati per pc",
  "sceltaContraente": "23-AFFIDAMENTO IN ECONOMIA - AFFIDAMENTO DIRETTO",
  "partecipanti": {
    "partecipante": {
      "codiceFiscale": "09777310153",
      "ragioneSociale": "NATIONAL INSTRUMENTS ITALY S.R.L."
    }
  },
  "aggiudicatari": {
    "aggiudicatario": {
      "codiceFiscale": "09777310153",
      "ragioneSociale": "NATIONAL INSTRUMENTS ITALY S.R.L."
    }
  },
  "importoAggiudicazione": "318.60",
  "tempiCompletamento": {
    "dataInizio": "2017-02-20",
    "dataUltimazione": "2017-02-20"
  },
  "importoSommeLiquidate": "318.60"
}