{
  "cig": "Z4612BC19B",
  "strutturaProponente": {
    "codiceFiscaleProp": "80088230018",
    "denominazione": "Universit\u00c3\u00a0 degli Studi di Torino"
  },
  "oggetto": "B.O. 4/62/65/77-2015 GAS COMPRESSI  - SIAD - SOCIETA' ITALIANA ACETILENE & DERIVATI S.P.A. SIAD S.P.A.",
  "sceltaContraente": "23-AFFIDAMENTO IN ECONOMIA - AFFIDAMENTO DIRETTO",
  "partecipanti": null,
  "aggiudicatari": null,
  "importoAggiudicazione": "11546.00",
  "tempiCompletamento": null,
  "importoSommeLiquidate": "2332.56"
}