{
  "cig": "Z4923CDEA9",
  "strutturaProponente": {
    "codiceFiscaleProp": "00518460019",
    "denominazione": "Politecnico di Torino"
  },
  "oggetto": "ORDINE CANCELLERIA ERREBIAN   CORAL 1737688-20180521",
  "sceltaContraente": "26-AFFIDAMENTO DIRETTO IN ADESIONE AD ACCORDO QUADRO/CONVENZIONE",
  "partecipanti": {
    "partecipante": {
      "codiceFiscale": "08397890586",
      "ragioneSociale": "ERREBIAN S.P.A."
    }
  },
  "aggiudicatari": {
    "aggiudicatario": {
      "codiceFiscale": "08397890586",
      "ragioneSociale": "ERREBIAN S.P.A."
    }
  },
  "importoAggiudicazione": "359.66",
  "tempiCompletamento": {
    "dataInizio": "2018-05-21",
    "dataUltimazione": "2018-05-21"
  },
  "importoSommeLiquidate": "359.67"
}