{
  "cig": "Z4F2449ADD",
  "strutturaProponente": {
    "codiceFiscaleProp": "00518460019",
    "denominazione": "Politecnico di Torino"
  },
  "oggetto": "Rinnovo annuale della manutenzione software dell'appliativo per i backup centrali. rinnovo Maintenance 12 mesi FCA34 (Scadenza 23 Settembre 2019 );",
  "sceltaContraente": "23-AFFIDAMENTO IN ECONOMIA - AFFIDAMENTO DIRETTO",
  "partecipanti": {
    "partecipante": [
      {
        "codiceFiscale": "05231661009",
        "ragioneSociale": "R1 S.P.A."
      },
      {
        "codiceFiscale": "07393280016",
        "ragioneSociale": "SISTEMI H.S. S.P.A."
      }
    ]
  },
  "aggiudicatari": {
    "aggiudicatario": {
      "codiceFiscale": "07393280016",
      "ragioneSociale": "SISTEMI H.S. S.P.A."
    }
  },
  "importoAggiudicazione": "26900.00",
  "tempiCompletamento": {
    "dataInizio": "2018-09-24",
    "dataUltimazione": "2019-09-23"
  },
  "importoSommeLiquidate": "26900.00"
}