{
  "cig": "Z5115C3685",
  "strutturaProponente": {
    "codiceFiscaleProp": "80088230018",
    "denominazione": "Universit\u00c3\u00a0 degli Studi di Torino"
  },
  "oggetto": "B.O. 460 DEL 11-09-2015",
  "sceltaContraente": "26-AFFIDAMENTO DIRETTO IN ADESIONE AD ACCORDO QUADRO/CONVENZIONE",
  "partecipanti": {
    "partecipante": {
      "codiceFiscale": "06111530637",
      "ragioneSociale": "AIESI HOSPITAL SERVICE"
    }
  },
  "aggiudicatari": {
    "aggiudicatario": {
      "codiceFiscale": "06111530637",
      "ragioneSociale": "AIESI HOSPITAL SERVICE"
    }
  },
  "importoAggiudicazione": "710.24",
  "tempiCompletamento": {
    "dataInizio": "2015-09-22"
  },
  "importoSommeLiquidate": "710.24"
}