{
  "cig": "Z5223DB9C5",
  "strutturaProponente": {
    "codiceFiscaleProp": "00518460019",
    "denominazione": "Politecnico di Torino"
  },
  "oggetto": "Servizio coffee break  durante convegno \"PDEs friends\"- Politecnico di Torino - 21 - 22 giugno 2018 -",
  "sceltaContraente": "23-AFFIDAMENTO IN ECONOMIA - AFFIDAMENTO DIRETTO",
  "partecipanti": {
    "partecipante": {
      "codiceFiscale": "07621400014",
      "ragioneSociale": "MEETING SERVICE CATERING SOC. COOP. A. R.L. ONLUS"
    }
  },
  "aggiudicatari": {
    "aggiudicatario": {
      "codiceFiscale": "07621400014",
      "ragioneSociale": "MEETING SERVICE CATERING SOC. COOP. A. R.L. ONLUS"
    }
  },
  "importoAggiudicazione": "438.00",
  "tempiCompletamento": {
    "dataInizio": "2018-06-04",
    "dataUltimazione": "2018-06-04"
  },
  "importoSommeLiquidate": "438.00"
}