{
  "cig": "Z5222CCB1E",
  "strutturaProponente": {
    "codiceFiscaleProp": "00518460019",
    "denominazione": "Politecnico di Torino"
  },
  "oggetto": "Servizio ambulanza per sessione laurea 19 20 marzo",
  "sceltaContraente": "23-AFFIDAMENTO IN ECONOMIA - AFFIDAMENTO DIRETTO",
  "partecipanti": {
    "partecipante": {
      "codiceFiscale": "11053490014",
      "ragioneSociale": "CROCE ROSSA ITALIANA COMITATO LOCALE DI MONCALIERI ONLUS"
    }
  },
  "aggiudicatari": {
    "aggiudicatario": {
      "codiceFiscale": "11053490014",
      "ragioneSociale": "CROCE ROSSA ITALIANA COMITATO LOCALE DI MONCALIERI ONLUS"
    }
  },
  "importoAggiudicazione": "425.00",
  "tempiCompletamento": {
    "dataInizio": "2018-03-14",
    "dataUltimazione": "2018-03-30"
  },
  "importoSommeLiquidate": "425.00"
}