{
  "cig": "Z591FFBFC0",
  "strutturaProponente": {
    "codiceFiscaleProp": "00518460019",
    "denominazione": "Politecnico di Torino"
  },
  "oggetto": "Rinnovo 2018 dell'abbonamento a Urbadoc - ISSN 2553-6710",
  "sceltaContraente": "23-AFFIDAMENTO IN ECONOMIA - AFFIDAMENTO DIRETTO",
  "partecipanti": {
    "partecipante": {
      "codiceFiscale": "03106600483",
      "ragioneSociale": "CASALINI LIBRI S.P.A."
    }
  },
  "aggiudicatari": {
    "aggiudicatario": {
      "codiceFiscale": "03106600483",
      "ragioneSociale": "CASALINI LIBRI S.P.A."
    }
  },
  "importoAggiudicazione": "1176.00",
  "tempiCompletamento": {
    "dataInizio": "2017-12-31",
    "dataUltimazione": "2018-12-31"
  },
  "importoSommeLiquidate": "1176.00"
}