{
  "cig": "Z5D2528C9A",
  "strutturaProponente": {
    "codiceFiscaleProp": "00518460019",
    "denominazione": "Politecnico di Torino"
  },
  "oggetto": "Taratura di sonde campione di riferimento  (LAT 139 Sezione Temperatura)",
  "sceltaContraente": "23-AFFIDAMENTO IN ECONOMIA - AFFIDAMENTO DIRETTO",
  "partecipanti": {
    "partecipante": {
      "codiceFiscale": "00000000000",
      "ragioneSociale": "UNIVERZA V LJUBLJANI FAKULTETA ZA ELEKTROTEHNIKO"
    }
  },
  "aggiudicatari": {
    "aggiudicatario": {
      "codiceFiscale": "00000000000",
      "ragioneSociale": "UNIVERZA V LJUBLJANI FAKULTETA ZA ELEKTROTEHNIKO"
    }
  },
  "importoAggiudicazione": "6142.50",
  "tempiCompletamento": {
    "dataInizio": "2018-10-04",
    "dataUltimazione": "2018-10-04"
  },
  "importoSommeLiquidate": "00.00"
}