{
  "cig": "Z60202DBD1",
  "strutturaProponente": {
    "codiceFiscaleProp": "00518460019",
    "denominazione": "Politecnico di Torino"
  },
  "oggetto": "Pernottamento ospiti del DISMA c/o struttura alberghiera in Torino - ottobre 2017",
  "sceltaContraente": "23-AFFIDAMENTO IN ECONOMIA - AFFIDAMENTO DIRETTO",
  "partecipanti": {
    "partecipante": {
      "codiceFiscale": "10184350014",
      "ragioneSociale": "Dock  srl"
    }
  },
  "aggiudicatari": {
    "aggiudicatario": {
      "codiceFiscale": "10184350014",
      "ragioneSociale": "Dock  srl"
    }
  },
  "importoAggiudicazione": "164.40",
  "tempiCompletamento": {
    "dataInizio": "2017-04-04",
    "dataUltimazione": "2017-04-04"
  },
  "importoSommeLiquidate": "164.40"
}