{
  "cig": "Z651E9A3CC",
  "strutturaProponente": {
    "codiceFiscaleProp": "00518460019",
    "denominazione": "Politecnico di Torino"
  },
  "oggetto": "Pernottamento nostro docente c/o Hotel a Salerno - convegno giugno 2017",
  "sceltaContraente": "23-AFFIDAMENTO IN ECONOMIA - AFFIDAMENTO DIRETTO",
  "partecipanti": {
    "partecipante": {
      "codiceFiscale": "00687880641",
      "ragioneSociale": "ROULETTE AGENCY S.r.l."
    }
  },
  "aggiudicatari": {
    "aggiudicatario": {
      "codiceFiscale": "00687880641",
      "ragioneSociale": "ROULETTE AGENCY S.r.l."
    }
  },
  "importoAggiudicazione": "340.00",
  "tempiCompletamento": {
    "dataInizio": "2017-05-15",
    "dataUltimazione": "2017-05-15"
  },
  "importoSommeLiquidate": "340.00"
}