{
  "cig": "Z731DCF456",
  "strutturaProponente": {
    "codiceFiscaleProp": "00518460019",
    "denominazione": "Politecnico di Torino"
  },
  "oggetto": "PLASMA CITRATO\nORDINE A SEGUITO GARA MEPA APERTA A TUTTI I FORNITORI DEL BANDO BSS DESERTA",
  "sceltaContraente": "23-AFFIDAMENTO IN ECONOMIA - AFFIDAMENTO DIRETTO",
  "partecipanti": {
    "partecipante": {
      "codiceFiscale": "12410660158",
      "ragioneSociale": "TEBU-BIO SRL  a socio unico"
    }
  },
  "aggiudicatari": {
    "aggiudicatario": {
      "codiceFiscale": "12410660158",
      "ragioneSociale": "TEBU-BIO SRL  a socio unico"
    }
  },
  "importoAggiudicazione": "463.00",
  "tempiCompletamento": {
    "dataInizio": "2017-03-17",
    "dataUltimazione": "2017-03-17"
  },
  "importoSommeLiquidate": "463.00"
}