{
  "cig": "Z751EADCF5",
  "strutturaProponente": {
    "codiceFiscaleProp": "00518460019",
    "denominazione": "Politecnico di Torino"
  },
  "oggetto": "MANUTENZIONE STRUMENTO SETARAM",
  "sceltaContraente": "23-AFFIDAMENTO IN ECONOMIA - AFFIDAMENTO DIRETTO",
  "partecipanti": {
    "partecipante": {
      "codiceFiscale": "08799660157",
      "ragioneSociale": "AUTOMATION SRL"
    }
  },
  "aggiudicatari": {
    "aggiudicatario": {
      "codiceFiscale": "08799660157",
      "ragioneSociale": "AUTOMATION SRL"
    }
  },
  "importoAggiudicazione": "1400.00",
  "tempiCompletamento": {
    "dataInizio": "2017-05-26",
    "dataUltimazione": "2017-05-26"
  },
  "importoSommeLiquidate": "1400.00"
}