{
  "cig": "Z841D61027",
  "strutturaProponente": {
    "codiceFiscaleProp": "00518460019",
    "denominazione": "Politecnico di Torino"
  },
  "oggetto": "CENTRIFUGA DA BANCO E ROTORE\nGARA MEPA APERTA A TUTTI I FORNITORI DEL BANDO BSS",
  "sceltaContraente": "23-AFFIDAMENTO IN ECONOMIA - AFFIDAMENTO DIRETTO",
  "partecipanti": {
    "partecipante": {
      "codiceFiscale": "01022690364",
      "ragioneSociale": "EXACTA+OPTECH LABCENTER S.P.A."
    }
  },
  "aggiudicatari": {
    "aggiudicatario": {
      "codiceFiscale": "01022690364",
      "ragioneSociale": "EXACTA+OPTECH LABCENTER S.P.A."
    }
  },
  "importoAggiudicazione": "5060.00",
  "tempiCompletamento": {
    "dataInizio": "2017-03-08",
    "dataUltimazione": "2017-03-08"
  },
  "importoSommeLiquidate": "5060.00"
}