{
  "cig": "Z871D26C89",
  "strutturaProponente": {
    "codiceFiscaleProp": "00518460019",
    "denominazione": "Politecnico di Torino"
  },
  "oggetto": "Servizio di manutenzione annuale sensori GAS DISAT",
  "sceltaContraente": "23-AFFIDAMENTO IN ECONOMIA - AFFIDAMENTO DIRETTO",
  "partecipanti": {
    "partecipante": [
      {
        "codiceFiscale": "00209070168",
        "ragioneSociale": "SIAD - SOCIETA' ITALIANA ACETILENE & DERIVATI S.P.A."
      },
      {
        "codiceFiscale": "12906300152",
        "ragioneSociale": "AIR LIQUIDE SPA"
      },
      {
        "codiceFiscale": "02670240585",
        "ragioneSociale": "LINDE GAS ITALIA SRL"
      },
      {
        "codiceFiscale": "08804430158",
        "ragioneSociale": "SAPIO PRODUZIONE IDROGENO OSSIGENO S.R.L."
      },
      {
        "codiceFiscale": "08418350966",
        "ragioneSociale": "RIVOIRA GAS S.R.L."
      }
    ]
  },
  "aggiudicatari": {
    "aggiudicatario": {
      "codiceFiscale": "00209070168",
      "ragioneSociale": "SIAD - SOCIETA' ITALIANA ACETILENE & DERIVATI S.P.A."
    }
  },
  "importoAggiudicazione": "4560.00",
  "tempiCompletamento": {
    "dataInizio": "2017-02-20",
    "dataUltimazione": "2017-02-20"
  },
  "importoSommeLiquidate": "4560.00"
}