{
  "cig": "Z921B1C806",
  "strutturaProponente": {
    "codiceFiscaleProp": "80088230018",
    "denominazione": "Universita' degli Studi di Torino - Struttura Didattica Speciale di Veterinaria"
  },
  "oggetto": "acquisto fieno primo taglio",
  "sceltaContraente": "23-AFFIDAMENTO IN ECONOMIA - AFFIDAMENTO DIRETTO",
  "partecipanti": {
    "partecipante": {
      "codiceFiscale": "10309570017",
      "ragioneSociale": "FRATELLI COMBA - SOCIETA' AGRICOLA SEMPLICE"
    }
  },
  "aggiudicatari": {
    "aggiudicatario": {
      "codiceFiscale": "10309570017",
      "ragioneSociale": "FRATELLI COMBA - SOCIETA' AGRICOLA SEMPLICE"
    }
  },
  "importoAggiudicazione": "1229.40",
  "tempiCompletamento": {
    "dataInizio": "2016-09-07",
    "dataUltimazione": "2016-09-07"
  },
  "importoSommeLiquidate": "1229.40"
}