{
  "cig": "Z98268780A",
  "strutturaProponente": {
    "codiceFiscaleProp": "80088230018",
    "denominazione": "Universita' degli Studi di Torino - SCIENZE DELLA SANITA' PUBBLICA E PEDIATRICHE"
  },
  "oggetto": "Rda n. 6904 Materiale di plastica per laboratorio Dott.ssa Francesca Gugliesi Prof. Santo Landolfo",
  "sceltaContraente": "23-AFFIDAMENTO IN ECONOMIA - AFFIDAMENTO DIRETTO",
  "partecipanti": {
    "partecipante": {
      "codiceFiscale": "07214840014",
      "ragioneSociale": "SAVATEC STRUMENTI S.R.L."
    }
  },
  "aggiudicatari": {
    "aggiudicatario": {
      "codiceFiscale": "07214840014",
      "ragioneSociale": "SAVATEC STRUMENTI S.R.L."
    }
  },
  "importoAggiudicazione": "383.35",
  "tempiCompletamento": {
    "dataInizio": "2018-12-28",
    "dataUltimazione": "2018-12-28"
  },
  "importoSommeLiquidate": "0.00"
}