{
  "cig": "Z99182998E",
  "strutturaProponente": {
    "codiceFiscaleProp": "80088230018",
    "denominazione": "Universit\u00c3\u00a0 degli Studi di Torino"
  },
  "oggetto": "materiale informatico",
  "sceltaContraente": "23-AFFIDAMENTO IN ECONOMIA - AFFIDAMENTO DIRETTO",
  "partecipanti": {
    "partecipante": {
      "codiceFiscale": "MNILVR53B53E716X",
      "ragioneSociale": "EMME DI MIANO ELVIRA"
    }
  },
  "aggiudicatari": {
    "aggiudicatario": {
      "codiceFiscale": "MNILVR53B53E716X",
      "ragioneSociale": "EMME DI MIANO ELVIRA"
    }
  },
  "importoAggiudicazione": "0.00",
  "tempiCompletamento": null,
  "importoSommeLiquidate": "65.80"
}