{
  "cig": "ZA01735C32",
  "strutturaProponente": {
    "codiceFiscaleProp": "80088230018",
    "denominazione": "Universit\u00c3\u00a0 degli Studi di Torino"
  },
  "oggetto": "Missione: Acquisto biglietto Trenitalia To-Rm A/R per il Prof. ALBERA ROBERTO (partecipazione alla Conferenza Permanente delle Facolt\u00c3\u00a0 e Scuole di Medicina del 26/11/2015 a Roma)",
  "sceltaContraente": "08-AFFIDAMENTO IN ECONOMIA - COTTIMO FIDUCIARIO",
  "partecipanti": null,
  "aggiudicatari": null,
  "importoAggiudicazione": "0.00",
  "tempiCompletamento": {
    "dataInizio": "2015-11-20",
    "dataUltimazione": "2016-01-22"
  },
  "importoSommeLiquidate": "1174.90"
}