{
  "cig": "ZA41E93B33",
  "strutturaProponente": {
    "codiceFiscaleProp": "00518460019",
    "denominazione": "Politecnico di Torino"
  },
  "oggetto": "iscrizione conferenza IEEE NETSOFT 2017",
  "sceltaContraente": "23-AFFIDAMENTO IN ECONOMIA - AFFIDAMENTO DIRETTO",
  "partecipanti": {
    "partecipante": {
      "codiceFiscale": "02599851207",
      "ragioneSociale": "MOMEDA EVENTI S.r.l."
    }
  },
  "aggiudicatari": {
    "aggiudicatario": {
      "codiceFiscale": "02599851207",
      "ragioneSociale": "MOMEDA EVENTI S.r.l."
    }
  },
  "importoAggiudicazione": "573.77",
  "tempiCompletamento": {
    "dataInizio": "2017-07-03",
    "dataUltimazione": "2017-07-07"
  },
  "importoSommeLiquidate": "573.77"
}