{
  "cig": "ZA61B00489",
  "strutturaProponente": {
    "codiceFiscaleProp": "80088230018",
    "denominazione": "Universita' degli Studi di Torino - SCIENZE AGRARIE, FORESTALI E ALIMENTARI"
  },
  "oggetto": "HOTEL 14-16/9/2016- DEVECCHI - BOLZANO",
  "sceltaContraente": "23-AFFIDAMENTO IN ECONOMIA - AFFIDAMENTO DIRETTO",
  "partecipanti": {
    "partecipante": {
      "codiceFiscale": "09668370019",
      "ragioneSociale": "SI VA' Snc"
    }
  },
  "aggiudicatari": {
    "aggiudicatario": {
      "codiceFiscale": "09668370019",
      "ragioneSociale": "SI VA' Snc"
    }
  },
  "importoAggiudicazione": "12.30",
  "tempiCompletamento": {
    "dataInizio": "2016-09-14",
    "dataUltimazione": "2016-09-16"
  },
  "importoSommeLiquidate": "12.30"
}