{
  "cig": "ZAD1D75FBD",
  "strutturaProponente": {
    "codiceFiscaleProp": "00518460019",
    "denominazione": "Politecnico di Torino"
  },
  "oggetto": "PUBBLICAZIONE ARTICOLO IEEE - USD 1295 - FATTURA N. 1-9173352095",
  "sceltaContraente": "23-AFFIDAMENTO IN ECONOMIA - AFFIDAMENTO DIRETTO",
  "partecipanti": {
    "partecipante": {
      "identificativoFiscaleEstero": "131656633",
      "ragioneSociale": "IEEE"
    }
  },
  "aggiudicatari": {
    "aggiudicatario": {
      "identificativoFiscaleEstero": "131656633",
      "ragioneSociale": "IEEE"
    }
  },
  "importoAggiudicazione": "1214.00",
  "tempiCompletamento": {
    "dataInizio": "2017-02-20",
    "dataUltimazione": "2017-02-20"
  },
  "importoSommeLiquidate": "00.00"
}