{
  "cig": "ZB7159AE78",
  "strutturaProponente": {
    "codiceFiscaleProp": "80088230018",
    "denominazione": "Universit\u00c3\u00a0 degli Studi di Torino"
  },
  "oggetto": "b.o.n.241 del 12-10-2015 riproduzioni fotografiche Prin Magnaldi Biblioteca Angelica- Mario Setter",
  "sceltaContraente": "23-AFFIDAMENTO IN ECONOMIA - AFFIDAMENTO DIRETTO",
  "partecipanti": null,
  "aggiudicatari": null,
  "importoAggiudicazione": "0.00",
  "tempiCompletamento": null,
  "importoSommeLiquidate": "63.00"
}