{
  "cig": "ZB818F4961",
  "strutturaProponente": {
    "codiceFiscaleProp": "80088230018",
    "denominazione": "Universit\u00c3\u00a0 degli Studi di Torino"
  },
  "oggetto": "B.O. 141/16 MACELLAZIONE E LAVORAZIONE SALAMI SUINI",
  "sceltaContraente": "23-AFFIDAMENTO IN ECONOMIA - AFFIDAMENTO DIRETTO",
  "partecipanti": {
    "partecipante": {
      "codiceFiscale": "03107020012",
      "ragioneSociale": "SALUMIFICIO NADIA SNC DI MORIONDO PIETRO &C."
    }
  },
  "aggiudicatari": null,
  "importoAggiudicazione": "909.00",
  "tempiCompletamento": null,
  "importoSommeLiquidate": "909.00"
}