{
  "cig": "ZBA23C5670",
  "strutturaProponente": {
    "codiceFiscaleProp": "00518460019",
    "denominazione": "Politecnico di Torino"
  },
  "oggetto": "CIG: ZBA23C5670 - FORNITURA DI N. 4 TABLET DA 12.9\" CON ACCESSORI ED ESTENSIONE DI GARANZIA - LOTTO 1",
  "sceltaContraente": "23-AFFIDAMENTO IN ECONOMIA - AFFIDAMENTO DIRETTO",
  "partecipanti": {
    "partecipante": [
      {
        "codiceFiscale": "05685740721",
        "ragioneSociale": "C&C  CONSULTING  S.R.L."
      },
      {
        "codiceFiscale": "08687680960",
        "ragioneSociale": "SOLPA srl"
      },
      {
        "codiceFiscale": "NSTLSN74M26F158R",
        "ragioneSociale": "ANASTASI ALESSANDRO ANASTASI ALESSANDRO"
      },
      {
        "codiceFiscale": "05984211218",
        "ragioneSociale": "R-STORE spa"
      }
    ]
  },
  "aggiudicatari": {
    "aggiudicatario": {
      "codiceFiscale": "NSTLSN74M26F158R",
      "ragioneSociale": "ANASTASI ALESSANDRO ANASTASI ALESSANDRO"
    }
  },
  "importoAggiudicazione": "5601.60",
  "tempiCompletamento": {
    "dataInizio": "2018-06-13",
    "dataUltimazione": "2018-06-13"
  },
  "importoSommeLiquidate": "5601.60"
}