{
  "cig": "ZC02637E68",
  "strutturaProponente": {
    "codiceFiscaleProp": "00518460019",
    "denominazione": "Politecnico di Torino"
  },
  "oggetto": "ZC02637E68 RINNOVO BIENNALE MAINTENANCE LICENZE ALTAIR LICENZE LAIB+LICENZE RICERCA E TEAM STUDENTESCHI DAL 15-01-2019 AL 14-01-2021",
  "sceltaContraente": "23-AFFIDAMENTO IN ECONOMIA - AFFIDAMENTO DIRETTO",
  "partecipanti": {
    "partecipante": {
      "codiceFiscale": "06670490017",
      "ragioneSociale": "ALTAIR ENGINEERING S.R.L"
    }
  },
  "aggiudicatari": {
    "aggiudicatario": {
      "codiceFiscale": "06670490017",
      "ragioneSociale": "ALTAIR ENGINEERING S.R.L"
    }
  },
  "importoAggiudicazione": "26000.00",
  "tempiCompletamento": {
    "dataInizio": "2018-12-31",
    "dataUltimazione": "2021-01-14"
  },
  "importoSommeLiquidate": "00.00"
}