{
  "cig": "ZC21B02C6B",
  "strutturaProponente": {
    "codiceFiscaleProp": "80088230018",
    "denominazione": "Universita' degli Studi di Torino - FISICA"
  },
  "oggetto": "Biglietto Torino-Napoli-Paestum 12/9/2016 Paestum-Salerno 14/9/2016 Dott. A. De Bortoli partecipazione Scuola Estiva Netval",
  "sceltaContraente": "23-AFFIDAMENTO IN ECONOMIA - AFFIDAMENTO DIRETTO",
  "partecipanti": {
    "partecipante": {
      "codiceFiscale": "00465850014",
      "ragioneSociale": "EDENTOURS S.N.C."
    }
  },
  "aggiudicatari": {
    "aggiudicatario": {
      "codiceFiscale": "00465850014",
      "ragioneSociale": "EDENTOURS S.N.C."
    }
  },
  "importoAggiudicazione": "141.37",
  "tempiCompletamento": {
    "dataInizio": "2016-09-12",
    "dataUltimazione": "2016-09-14"
  },
  "importoSommeLiquidate": "141.37"
}