{
  "cig": "ZC32385169",
  "strutturaProponente": {
    "codiceFiscaleProp": "00518460019",
    "denominazione": "Politecnico di Torino"
  },
  "oggetto": "Terza edizione Exploring eLearning",
  "sceltaContraente": "23-AFFIDAMENTO IN ECONOMIA - AFFIDAMENTO DIRETTO",
  "partecipanti": {
    "partecipante": {
      "codiceFiscale": "01405830439",
      "ragioneSociale": "AMICUCCI FORMAZIONE S.R.L."
    }
  },
  "aggiudicatari": {
    "aggiudicatario": {
      "codiceFiscale": "01405830439",
      "ragioneSociale": "AMICUCCI FORMAZIONE S.R.L."
    }
  },
  "importoAggiudicazione": "1050.00",
  "tempiCompletamento": {
    "dataInizio": "2018-06-06",
    "dataUltimazione": "2018-06-07"
  },
  "importoSommeLiquidate": "1050.00"
}