{
  "cig": "ZC41E9809D",
  "strutturaProponente": {
    "codiceFiscaleProp": "00518460019",
    "denominazione": "Politecnico di Torino"
  },
  "oggetto": "BOMBO0LA CO2 E RIDUTTORE",
  "sceltaContraente": "23-AFFIDAMENTO IN ECONOMIA - AFFIDAMENTO DIRETTO",
  "partecipanti": {
    "partecipante": [
      {
        "codiceFiscale": "01738810975",
        "ragioneSociale": "AIR LIQUIDE SANITA' SERVICE SPA"
      },
      {
        "codiceFiscale": "02670240585",
        "ragioneSociale": "LINDE GAS ITALIA SRL"
      },
      {
        "codiceFiscale": "08418350966",
        "ragioneSociale": "RIVOIRA GAS S.R.L."
      }
    ]
  },
  "aggiudicatari": {
    "aggiudicatario": {
      "codiceFiscale": "01738810975",
      "ragioneSociale": "AIR LIQUIDE SANITA' SERVICE SPA"
    }
  },
  "importoAggiudicazione": "380.00",
  "tempiCompletamento": {
    "dataInizio": "2017-06-14",
    "dataUltimazione": "2017-06-14"
  },
  "importoSommeLiquidate": "380.00"
}