{
  "cig": "ZD3265C6FC",
  "strutturaProponente": {
    "codiceFiscaleProp": "80088230018",
    "denominazione": "Universita' degli Studi di Torino - DENTAL SCHOOL CENTRO DI ECCELLENZA PER LA RICERCA, LA DIDATTICA E L'ASSISTENZA IN CAMPO ODONTOSTOMATOLOGICO"
  },
  "oggetto": "DOTT. DEREGIBUS  - SERVIZIO DI CATERING PER TESI MASTER IN GESTIONE CLINICA DEI CASI ORTODONTICI COMPLESSI AA 2017/18",
  "sceltaContraente": "08-AFFIDAMENTO IN ECONOMIA - COTTIMO FIDUCIARIO",
  "partecipanti": {
    "partecipante": {
      "codiceFiscale": "09847660017",
      "ragioneSociale": "TRAMEZZINO ITI' TORINO Srl"
    }
  },
  "aggiudicatari": {
    "aggiudicatario": {
      "codiceFiscale": "09847660017",
      "ragioneSociale": "TRAMEZZINO ITI' TORINO Srl"
    }
  },
  "importoAggiudicazione": "650.00",
  "tempiCompletamento": {
    "dataInizio": "2018-12-21",
    "dataUltimazione": "2018-12-21"
  },
  "importoSommeLiquidate": "0.00"
}