{
  "cig": "ZD5265938F",
  "strutturaProponente": {
    "codiceFiscaleProp": "80088230018",
    "denominazione": "Universita' degli Studi di Torino - PSICOLOGIA"
  },
  "oggetto": "MEPA TD 767637 - LICENZE ATLAS - MOSSO (RdA 7062)",
  "sceltaContraente": "23-AFFIDAMENTO IN ECONOMIA - AFFIDAMENTO DIRETTO",
  "partecipanti": {
    "partecipante": {
      "codiceFiscale": "01501640666",
      "ragioneSociale": "TStat s.r.l. TSTAT"
    }
  },
  "aggiudicatari": {
    "aggiudicatario": {
      "codiceFiscale": "01501640666",
      "ragioneSociale": "TStat s.r.l. TSTAT"
    }
  },
  "importoAggiudicazione": "7966.00",
  "tempiCompletamento": {
    "dataInizio": "2018-12-20",
    "dataUltimazione": "2019-01-21"
  },
  "importoSommeLiquidate": "0.00"
}