{
  "cig": "ZD7234419F",
  "strutturaProponente": {
    "codiceFiscaleProp": "00518460019",
    "denominazione": "Politecnico di Torino"
  },
  "oggetto": "integrazione intervento manutenzione",
  "sceltaContraente": "23-AFFIDAMENTO IN ECONOMIA - AFFIDAMENTO DIRETTO",
  "partecipanti": {
    "partecipante": {
      "codiceFiscale": "02542350042",
      "ragioneSociale": "EUROTEC SCARL"
    }
  },
  "aggiudicatari": {
    "aggiudicatario": {
      "codiceFiscale": "02542350042",
      "ragioneSociale": "EUROTEC SCARL"
    }
  },
  "importoAggiudicazione": "925.00",
  "tempiCompletamento": {
    "dataInizio": "2018-05-02",
    "dataUltimazione": "2018-05-02"
  },
  "importoSommeLiquidate": "925.00"
}