{
  "cig": "ZDA22F17C7",
  "strutturaProponente": {
    "codiceFiscaleProp": "00518460019",
    "denominazione": "Politecnico di Torino"
  },
  "oggetto": "Acquisto licenze software mathematica - RDA 19",
  "sceltaContraente": "23-AFFIDAMENTO IN ECONOMIA - AFFIDAMENTO DIRETTO",
  "partecipanti": {
    "partecipante": {
      "codiceFiscale": "01408650511",
      "ragioneSociale": "ADALTA S.N.C. DI FAZZI MARCO E MARCANTONI GIAMPAOLO"
    }
  },
  "aggiudicatari": {
    "aggiudicatario": {
      "codiceFiscale": "01408650511",
      "ragioneSociale": "ADALTA S.N.C. DI FAZZI MARCO E MARCANTONI GIAMPAOLO"
    }
  },
  "importoAggiudicazione": "20483.34",
  "tempiCompletamento": {
    "dataInizio": "2018-03-29",
    "dataUltimazione": "2018-03-29"
  },
  "importoSommeLiquidate": "6827.78"
}