{
  "cig": "ZDB1A9E162",
  "strutturaProponente": {
    "codiceFiscaleProp": "80088230018",
    "denominazione": "Universit\u00c3\u00a0 degli Studi di Torino"
  },
  "oggetto": "generico uscita 75",
  "sceltaContraente": "23-AFFIDAMENTO IN ECONOMIA - AFFIDAMENTO DIRETTO",
  "partecipanti": {
    "partecipante": {
      "identificativoFiscaleEstero": null,
      "ragioneSociale": "ACADEMIE DES INSCRIPTIONS ET BELLES-LETTRES"
    }
  },
  "aggiudicatari": {
    "aggiudicatario": {
      "identificativoFiscaleEstero": null,
      "ragioneSociale": "ACADEMIE DES INSCRIPTIONS ET BELLES-LETTRES"
    }
  },
  "importoAggiudicazione": "4000.00",
  "tempiCompletamento": null,
  "importoSommeLiquidate": "0.00"
}