{
  "cig": "ZE21E09D30",
  "strutturaProponente": {
    "codiceFiscaleProp": "00518460019",
    "denominazione": "Politecnico di Torino"
  },
  "oggetto": "CIG ZE21E09D30 - ACQUISTO LED E PSD",
  "sceltaContraente": "23-AFFIDAMENTO IN ECONOMIA - AFFIDAMENTO DIRETTO",
  "partecipanti": {
    "partecipante": [
      {
        "codiceFiscale": "10247190159",
        "ragioneSociale": "HAMAMATSU PHOTONICS ITALIA S.R.L."
      },
      {
        "codiceFiscale": "10765880157",
        "ragioneSociale": "DISTRELEC ITALIA S.R.L."
      }
    ]
  },
  "aggiudicatari": {
    "aggiudicatario": {
      "codiceFiscale": "10247190159",
      "ragioneSociale": "HAMAMATSU PHOTONICS ITALIA S.R.L."
    }
  },
  "importoAggiudicazione": "434.09",
  "tempiCompletamento": {
    "dataInizio": "2017-05-08",
    "dataUltimazione": "2017-05-08"
  },
  "importoSommeLiquidate": "436.58"
}