{
  "cig": "ZE6259E6C5",
  "strutturaProponente": {
    "codiceFiscaleProp": "00518460019",
    "denominazione": "Politecnico di Torino"
  },
  "oggetto": "Lettori di badge Siemens modello AR6181-MX con modifica per lettura tecnologica Calypso",
  "sceltaContraente": "23-AFFIDAMENTO IN ECONOMIA - AFFIDAMENTO DIRETTO",
  "partecipanti": {
    "partecipante": {
      "codiceFiscale": "00751160151",
      "ragioneSociale": "SIEMENS S.P.A."
    }
  },
  "aggiudicatari": {
    "aggiudicatario": {
      "codiceFiscale": "00751160151",
      "ragioneSociale": "SIEMENS S.P.A."
    }
  },
  "importoAggiudicazione": "4680.00",
  "tempiCompletamento": {
    "dataInizio": "2018-10-17",
    "dataUltimazione": "2018-10-17"
  },
  "importoSommeLiquidate": "00.00"
}