{
  "cig": "ZED2240F44",
  "strutturaProponente": {
    "codiceFiscaleProp": "00518460019",
    "denominazione": "Politecnico di Torino"
  },
  "oggetto": "servizio di Relocation e Assistenza Straordinaria Sistema EOSINT M270 SI0846",
  "sceltaContraente": "23-AFFIDAMENTO IN ECONOMIA - AFFIDAMENTO DIRETTO",
  "partecipanti": {
    "partecipante": {
      "codiceFiscale": "12137280157",
      "ragioneSociale": "EOS s.r.l. Electro Optical Systems"
    }
  },
  "aggiudicatari": {
    "aggiudicatario": {
      "codiceFiscale": "12137280157",
      "ragioneSociale": "EOS s.r.l. Electro Optical Systems"
    }
  },
  "importoAggiudicazione": "12050.87",
  "tempiCompletamento": {
    "dataInizio": "2018-02-06",
    "dataUltimazione": "2018-12-31"
  },
  "importoSommeLiquidate": "12050.87"
}