{
  "cig": "ZF01F1666F",
  "strutturaProponente": {
    "codiceFiscaleProp": "00518460019",
    "denominazione": "Politecnico di Torino"
  },
  "oggetto": "CIG ZF01F1666F - Development Program e Membership Fees annuali per il Consorzio Top-IX anno 2017",
  "sceltaContraente": "23-AFFIDAMENTO IN ECONOMIA - AFFIDAMENTO DIRETTO",
  "partecipanti": {
    "partecipante": {
      "codiceFiscale": "08445410015",
      "ragioneSociale": "CONSORZIO TOPIX - TORINO E PIEMONTE INTERNET EXCHANGE"
    }
  },
  "aggiudicatari": {
    "aggiudicatario": {
      "codiceFiscale": "08445410015",
      "ragioneSociale": "CONSORZIO TOPIX - TORINO E PIEMONTE INTERNET EXCHANGE"
    }
  },
  "importoAggiudicazione": "22000.00",
  "tempiCompletamento": {
    "dataInizio": "2017-01-01",
    "dataUltimazione": "2017-12-31"
  },
  "importoSommeLiquidate": "22000.00"
}