{
  "cig": "ZF123508CD",
  "strutturaProponente": {
    "codiceFiscaleProp": "00518460019",
    "denominazione": "Politecnico di Torino"
  },
  "oggetto": "Acquisto licenze Dropbox Bus Advanced - RDA 23",
  "sceltaContraente": "23-AFFIDAMENTO IN ECONOMIA - AFFIDAMENTO DIRETTO",
  "partecipanti": {
    "partecipante": {
      "codiceFiscale": "05185750014",
      "ragioneSociale": "REKORDATA S.R.L."
    }
  },
  "aggiudicatari": {
    "aggiudicatario": {
      "codiceFiscale": "05185750014",
      "ragioneSociale": "REKORDATA S.R.L."
    }
  },
  "importoAggiudicazione": "1344.00",
  "tempiCompletamento": {
    "dataInizio": "2018-05-15",
    "dataUltimazione": "2018-05-15"
  },
  "importoSommeLiquidate": "840.00"
}