{
  "cig": "ZF2242ED3B",
  "strutturaProponente": {
    "codiceFiscaleProp": "00518460019",
    "denominazione": "Politecnico di Torino"
  },
  "oggetto": "Affidamento dell\u00e2\u0080\u0099incarico professionale di CSP e CSE in relazione ai lavori di manutenzione, ristrutturazione e riqualificazione da eseguirsi negli edifici di propriet\u00c3\u00a0 del Politecnico di Torino\u00e2\u0080\u009d.",
  "sceltaContraente": "23-AFFIDAMENTO IN ECONOMIA - AFFIDAMENTO DIRETTO",
  "partecipanti": {
    "partecipante": [
      {
        "codiceFiscale": "GLRGRG63A03A479N",
        "ragioneSociale": "Arch. Giorgio Gilardetti"
      },
      {
        "codiceFiscale": "CHSDRN59T58L219Q",
        "ragioneSociale": "Arch. Doriana Chiesa"
      },
      {
        "codiceFiscale": "ZNZNCL76A25H294B",
        "ragioneSociale": "Ing. Nicol\u00c3\u00b2 ZANZINI"
      },
      {
        "codiceFiscale": "VGGSRG61B17L219F",
        "ragioneSociale": "Ing. Sergio VOGOGNA"
      }
    ]
  },
  "aggiudicatari": {
    "aggiudicatario": {
      "codiceFiscale": "GLRGRG63A03A479N",
      "ragioneSociale": "Arch. Giorgio Gilardetti"
    }
  },
  "importoAggiudicazione": "39500.00",
  "tempiCompletamento": {
    "dataInizio": "2018-08-03"
  },
  "importoSommeLiquidate": "00.00"
}