{
  "cig": "ZF324FC7F4",
  "strutturaProponente": {
    "codiceFiscaleProp": "00518460019",
    "denominazione": "Politecnico di Torino"
  },
  "oggetto": "Acquisto shopper  per ospiti Convegno \"Trails in quantum mechanics and Surroundings\" - settembre 2018",
  "sceltaContraente": "23-AFFIDAMENTO IN ECONOMIA - AFFIDAMENTO DIRETTO",
  "partecipanti": {
    "partecipante": {
      "codiceFiscale": "97529720019",
      "ragioneSociale": "POLINCONTRI"
    }
  },
  "aggiudicatari": {
    "aggiudicatario": {
      "codiceFiscale": "97529720019",
      "ragioneSociale": "POLINCONTRI"
    }
  },
  "importoAggiudicazione": "114.75",
  "tempiCompletamento": {
    "dataInizio": "2018-07-11",
    "dataUltimazione": "2018-07-11"
  },
  "importoSommeLiquidate": "114.75"
}