{
  "cig": "ZF61D310C7",
  "strutturaProponente": {
    "codiceFiscaleProp": "00518460019",
    "denominazione": "Politecnico di Torino"
  },
  "oggetto": "cig ZF61D310C7  Acquisto software per la gestione delle cam su 3 synology nas",
  "sceltaContraente": "23-AFFIDAMENTO IN ECONOMIA - AFFIDAMENTO DIRETTO",
  "partecipanti": {
    "partecipante": [
      {
        "codiceFiscale": "09680340016",
        "ragioneSociale": "AXITALIA S.R.L. a socio unico"
      },
      {
        "codiceFiscale": "02778750246",
        "ragioneSociale": "SOLUZIONE UFFICIO S.R.L."
      }
    ]
  },
  "aggiudicatari": {
    "aggiudicatario": {
      "codiceFiscale": "02778750246",
      "ragioneSociale": "SOLUZIONE UFFICIO S.R.L."
    }
  },
  "importoAggiudicazione": "780.00",
  "tempiCompletamento": {
    "dataInizio": "2017-03-07",
    "dataUltimazione": "2017-03-07"
  },
  "importoSommeLiquidate": "780.00"
}